ingenii_quantum/__init__.py
ingenii_quantum/custom.py
ingenii_quantum/exercises.py
ingenii_quantum/visualizer.py
ingenii_quantum/data/core_test.csv
ingenii_quantum/data/core_test_fc10.npy
ingenii_quantum/data/core_test_fc6.npy
ingenii_quantum/data/edge-detection.png
ingenii_quantum/data/mammography.png
ingenii_quantum/data/mammography_mask.png
ingenii_quantum/data/pbdbind2016_core_test_3dnn.csv
ingenii_quantum/data/pdbbind2016_core_test.hdf
ingenii_quantum/data/refined_train.csv
ingenii_quantum/data/refined_train_fc10.npy
ingenii_quantum/data/refined_train_fc6.npy
ingenii_quantum/data/refined_val.csv
ingenii_quantum/data/refined_val_fc10.npy
ingenii_quantum/data/refined_val_fc6.npy
ingenii_quantum/data/ultrasound_image.png
ingenii_quantum/hybrid_networks/__init__.py
ingenii_quantum/hybrid_networks/edge_detection.py
ingenii_quantum/hybrid_networks/filters.py
ingenii_quantum/hybrid_networks/layers.py
ingenii_quantum/hybrid_networks/qinsp_filter.py
ingenii_quantum/hybrid_networks/statistics.py
ingenii_quantum/hybrid_networks/utils.py
ingenii_quantum/qubo/__init__.py
ingenii_quantum/qubo/graph.py
ingenii_quantum/qubo/segmentation.py
ingenii_quantum/tensor_networks/VBMF.py
ingenii_quantum/tensor_networks/__init__.py
ingenii_quantum/tensor_networks/tucker_decomposition.py
ingenii_quantum-0.1.1.dist-info/METADATA
ingenii_quantum-0.1.1.dist-info/WHEEL
ingenii_quantum-0.1.1.dist-info/dependency_links.txt
ingenii_quantum-0.1.1.dist-info/top_level.txt
ingenii_quantum-0.1.1.dist-info/RECORD
