Metadata-Version: 2.2
Name: ingenii-quantum
Version: 0.1.1
Summary: Quantum and quantum-inspired algorithms for machine learning.
Home-page: https://github.com/ingenii-solutions/ingenii-quantum-hybrid-networks
Author: Ingenii
Author-email: laia@ingenii.dev
Classifier: Programming Language :: Python :: 3
Classifier: License :: OSI Approved :: Mozilla Public License 2.0 (MPL 2.0)
Classifier: Operating System :: OS Independent
Requires-Dist: qiskit>=1.2
Requires-Dist: qiskit-aer>=0.15
Requires-Dist: qiskit-ibm-runtime>=0.31
Requires-Dist: scikit-learn
Requires-Dist: scipy
Requires-Dist: h5py
Requires-Dist: matplotlib
Requires-Dist: pylatexenc
Requires-Dist: torch
Requires-Dist: torchaudio
Requires-Dist: torchvision
Requires-Dist: torch-geometric
Requires-Dist: pennylane
Requires-Dist: tensorflow
Requires-Dist: numpy
Requires-Dist: tensorly
Requires-Dist: quimb
Requires-Dist: gurobipy
Dynamic: requires-dist
